MANIFEST.in
setup.py
requirements/base.txt
requirements/dev.txt
trading.etl.ohlcv.egg-info/PKG-INFO
trading.etl.ohlcv.egg-info/SOURCES.txt
trading.etl.ohlcv.egg-info/dependency_links.txt
trading.etl.ohlcv.egg-info/requires.txt
trading.etl.ohlcv.egg-info/top_level.txt
trading/etl/ohlcv/__init__.py
trading/etl/ohlcv/core/__init__.py
trading/etl/ohlcv/core/errors.py
trading/etl/ohlcv/core/metadata.py
trading/etl/ohlcv/core/ohlcv.py
trading/etl/ohlcv/tests/__init__.py
trading/etl/ohlcv/tests/test_core/__init__.py
trading/etl/ohlcv/tests/test_core/test_metadata.py
trading/etl/ohlcv/tests/test_core/test_ohlcv.py