Metadata-Version: 1.2
Name: trading.etl.ohlcv
Version: 0.0.2
Summary: Candles datatype for exchange market data ingestion.
Home-page: UNKNOWN
Author: Trading
License: UNKNOWN
Platform: UNKNOWN
Requires-Python: >=3.7
